disarray/__init__.py
disarray/metrics.py
disarray/version.py
disarray-0.2.0.dist-info/LICENSE
disarray-0.2.0.dist-info/METADATA
disarray-0.2.0.dist-info/WHEEL
disarray-0.2.0.dist-info/top_level.txt
disarray-0.2.0.dist-info/RECORD
