Metadata-Version: 2.1
Name: disarray
Version: 0.2.0
Summary: Calculate confusion matrix metrics from your pandas DataFrame
Home-page: https://github.com/arvkevi/disarray
Author: Kevin Arvai
Author-email: arvkevi@gmail.com
License: MIT
Download-URL: https://github.com/arvkevi/disarray/tarball/0.2.0
Keywords: machine learning-supervised learning
Platform: UNKNOWN
Classifier: Development Status :: 3 - Alpha
Classifier: Intended Audience :: Science/Research
Classifier: Topic :: Scientific/Engineering :: Information Analysis
Classifier: Programming Language :: Python :: 3
Requires-Dist: pandas (>=0.23.0)
Requires-Dist: numpy (>=0.14.2)
